setup.py
path_comment/__about__.py
path_comment/__init__.py
path_comment/cli.py
path_comment/config.py
path_comment/detectors.py
path_comment/file_handler.py
path_comment/injector.py
path_comment/processor.py
path_comment/py.typed
path_comment/welcome.py
path_comment_hook-0.1.0.dist-info/LICENSE
path_comment_hook-0.1.0.dist-info/METADATA
path_comment_hook-0.1.0.dist-info/WHEEL
path_comment_hook-0.1.0.dist-info/entry_points.txt
path_comment_hook-0.1.0.dist-info/RECORD
