Metadata-Version: 2.1
Name: path-comment-hook
Version: 0.1.0
Summary: Pre-commit hook that injects relative-path comments into source files
License: MIT
Keywords: pre-commit,hook,path,comment,header
Author: Shorzinator
Author-email: shorz2905@gmail.com
Maintainer: Shorzinator
Maintainer-email: shorz2905@gmail.com
Requires-Python: >=3.8,<4.0
Classifier: Development Status :: 4 - Beta
Classifier: Intended Audience :: Developers
Classifier: License :: OSI Approved :: MIT License
Classifier: Programming Language :: Python
Classifier: Programming Language :: Python :: 3
Classifier: Programming Language :: Python :: 3.8
Classifier: Programming Language :: Python :: 3.9
Classifier: Programming Language :: Python :: 3.10
Classifier: Programming Language :: Python :: 3.11
Classifier: Programming Language :: Python :: 3.12
Classifier: Programming Language :: Python :: Implementation :: CPython
Classifier: Topic :: Software Development :: Quality Assurance
Classifier: Topic :: Software Development :: Version Control
Requires-Dist: chardet (>=5.0.0,<6.0.0)
Requires-Dist: identify (>=2.5.0,<3.0.0)
Requires-Dist: rich (>=13.0.0,<14.0.0)
Requires-Dist: tomli (>=2.0.0,<3.0.0) ; python_version < "3.11"
Requires-Dist: typer (>=0.16.0,<0.17.0)
Project-URL: Documentation, https://github.com/Shorzinator/path-comment-hook#readme
Project-URL: Issues, https://github.com/Shorzinator/path-comment-hook/issues
Project-URL: Source, https://github.com/Shorzinator/path-comment-hook
